pytrafikverket/__init__.py
pytrafikverket/__main__.py
pytrafikverket/const.py
pytrafikverket/exceptions.py
pytrafikverket/filters.py
pytrafikverket/helpers.py
pytrafikverket/models.py
pytrafikverket/py.typed
pytrafikverket/trafikverket.py
pytrafikverket/trafikverket_camera.py
pytrafikverket/trafikverket_ferry.py
pytrafikverket/trafikverket_train.py
pytrafikverket/trafikverket_weather.py
pytrafikverket-1.1.1.dist-info/LICENSE
pytrafikverket-1.1.1.dist-info/METADATA
pytrafikverket-1.1.1.dist-info/WHEEL
pytrafikverket-1.1.1.dist-info/entry_points.txt
pytrafikverket-1.1.1.dist-info/RECORD
