Metadata-Version: 2.1
Name: pytrafikverket
Version: 1.1.1
Summary: Retrieve values from public API at the Swedish Transport Administration (Trafikverket).
Home-page: https://github.com/gjohansson-ST/pytrafikverket
License: MIT
Keywords: trafikverket,api,async,client
Author: G Johansson
Author-email: goran.johansson@shiftit.se
Maintainer: G Johansson
Maintainer-email: goran.johansson@shiftit.se
Requires-Python: >=3.11,<4.0
Classifier: Development Status :: 5 - Production/Stable
Classifier: Intended Audience :: Developers
Classifier: License :: OSI Approved :: MIT License
Classifier: Natural Language :: English
Classifier: Programming Language :: Python :: 3
Classifier: Programming Language :: Python :: 3.11
Classifier: Programming Language :: Python :: 3.12
Classifier: Programming Language :: Python :: 3.13
Classifier: Topic :: Software Development :: Libraries :: Python Modules
Requires-Dist: aiohttp (>=3.9.2)
Requires-Dist: aiozoneinfo (>=0.2.1)
Requires-Dist: lxml (>=5.1.0)
Requires-Dist: yarl (>=1.9.4)
Project-URL: Bug Tracker, https://github.com/gjohansson-ST/pytrafikverket/issues
Project-URL: Changelog, https://github.com/gjohansson-ST/pytrafikverket/releases
Project-URL: Documentation, https://github.com/gjohansson-ST/pytrafikverket
Project-URL: Repository, https://github.com/gjohansson-ST/pytrafikverket
